oaiv_btc/__init__.py
oaiv_btc/func.py
oaiv_btc-0.0.4.dist-info/METADATA
oaiv_btc-0.0.4.dist-info/WHEEL
oaiv_btc-0.0.4.dist-info/top_level.txt
oaiv_btc-0.0.4.dist-info/RECORD
